{
    "key": "group_6932cc338f014",
    "title": "Afbeelding | Ondersteuning",
    "fields": [
        {
            "key": "field_6932cea1eab6a",
            "label": "(Column 6\/12)",
            "name": "",
            "aria-label": "",
            "type": "acfe_column",
            "instructions": "",
            "required": 0,
            "conditional_logic": 0,
            "wrapper": {
                "width": "",
                "class": "",
                "id": ""
            },
            "columns": "6\/12",
            "endpoint": 0,
            "allow_in_bindings": 0,
            "wpml_cf_preferences": 2
        },
        {
            "key": "field_6932cef5eab6b",
            "label": "Label",
            "name": "label",
            "aria-label": "",
            "type": "text",
            "instructions": "",
            "required": 0,
            "conditional_logic": 0,
            "wrapper": {
                "width": "",
                "class": "",
                "id": ""
            },
            "default_value": "",
            "maxlength": "",
            "allow_in_bindings": 0,
            "placeholder": "",
            "prepend": "",
            "append": "",
            "wpml_cf_preferences": 2
        },
        {
            "key": "field_6932ceffeab6c",
            "label": "Tekst",
            "name": "txt",
            "aria-label": "",
            "type": "wysiwyg",
            "instructions": "",
            "required": 0,
            "conditional_logic": 0,
            "wrapper": {
                "width": "",
                "class": "",
                "id": ""
            },
            "default_value": "",
            "allow_in_bindings": 0,
            "tabs": "all",
            "toolbar": "full",
            "media_upload": 1,
            "delay": 0,
            "wpml_cf_preferences": 2
        },
        {
            "key": "field_6932cf11eab6d",
            "label": "Links",
            "name": "links",
            "aria-label": "",
            "type": "repeater",
            "instructions": "",
            "required": 0,
            "conditional_logic": 0,
            "wrapper": {
                "width": "",
                "class": "",
                "id": ""
            },
            "acfe_repeater_stylised_button": 0,
            "layout": "table",
            "pagination": 0,
            "min": 0,
            "max": 0,
            "collapsed": "",
            "button_label": "Nieuwe rij",
            "rows_per_page": 20,
            "wpml_cf_preferences": 1,
            "sub_fields": [
                {
                    "key": "field_6932cf2eeab6e",
                    "label": "link",
                    "name": "link",
                    "aria-label": "",
                    "type": "link",
                    "instructions": "",
                    "required": 0,
                    "conditional_logic": 0,
                    "wrapper": {
                        "width": "",
                        "class": "",
                        "id": ""
                    },
                    "return_format": "array",
                    "allow_in_bindings": 0,
                    "parent_repeater": "field_6932cf11eab6d",
                    "wpml_cf_preferences": 1
                }
            ]
        },
        {
            "key": "field_6932cf50eab6f",
            "label": "Knop",
            "name": "link_btn",
            "aria-label": "",
            "type": "link",
            "instructions": "",
            "required": 0,
            "conditional_logic": 0,
            "wrapper": {
                "width": "",
                "class": "",
                "id": ""
            },
            "return_format": "array",
            "allow_in_bindings": 0,
            "wpml_cf_preferences": 1
        },
        {
            "key": "field_6932cc33eab65",
            "label": "(Column 6\/12)",
            "name": "",
            "aria-label": "",
            "type": "acfe_column",
            "instructions": "",
            "required": 0,
            "conditional_logic": 0,
            "wrapper": {
                "width": "",
                "class": "",
                "id": ""
            },
            "columns": "6\/12",
            "endpoint": 0,
            "allow_in_bindings": 0,
            "wpml_cf_preferences": 2
        },
        {
            "key": "field_6932cc54eab66",
            "label": "Afbeelding (600x600)",
            "name": "img",
            "aria-label": "",
            "type": "image",
            "instructions": "",
            "required": 0,
            "conditional_logic": 0,
            "wrapper": {
                "width": "",
                "class": "",
                "id": ""
            },
            "uploader": "",
            "return_format": "id",
            "library": "all",
            "acfe_thumbnail": 0,
            "min_width": 600,
            "min_height": 600,
            "min_size": "",
            "max_width": "",
            "max_height": "",
            "max_size": 1,
            "mime_types": "",
            "allow_in_bindings": 0,
            "preview_size": "medium",
            "wpml_cf_preferences": 1
        },
        {
            "key": "field_6932cc63eab67",
            "label": "Contact icoon",
            "name": "icon",
            "aria-label": "",
            "type": "text",
            "instructions": "Plaats de naam van de icoon vanuit https:\/\/fonts.google.com\/icons",
            "required": 0,
            "conditional_logic": 0,
            "wrapper": {
                "width": "",
                "class": "",
                "id": ""
            },
            "default_value": "forward_to_inbox",
            "maxlength": "",
            "allow_in_bindings": 0,
            "placeholder": "",
            "prepend": "",
            "append": "",
            "wpml_cf_preferences": 2
        },
        {
            "key": "field_6932ccd8eab68",
            "label": "Chapeau",
            "name": "chapeau",
            "aria-label": "",
            "type": "text",
            "instructions": "De tekst boven de email",
            "required": 0,
            "conditional_logic": 0,
            "wrapper": {
                "width": "",
                "class": "",
                "id": ""
            },
            "default_value": "Direct support nodig?",
            "maxlength": "",
            "allow_in_bindings": 0,
            "placeholder": "",
            "prepend": "",
            "append": "",
            "wpml_cf_preferences": 2
        },
        {
            "key": "field_6932ce66eab69",
            "label": "Email",
            "name": "mail",
            "aria-label": "",
            "type": "text",
            "instructions": "Plaats hier een werkbare mail: naam@email.com",
            "required": 0,
            "conditional_logic": 0,
            "wrapper": {
                "width": "",
                "class": "",
                "id": ""
            },
            "default_value": "",
            "maxlength": "",
            "allow_in_bindings": 0,
            "placeholder": "",
            "prepend": "",
            "append": "",
            "wpml_cf_preferences": 2
        }
    ],
    "location": [
        [
            {
                "param": "post_type",
                "operator": "==",
                "value": "post"
            }
        ]
    ],
    "menu_order": 0,
    "position": "normal",
    "style": "default",
    "label_placement": "top",
    "instruction_placement": "label",
    "hide_on_screen": "",
    "active": false,
    "description": "",
    "show_in_rest": 0,
    "display_title": "",
    "acfe_autosync": [
        "json"
    ],
    "acfml_field_group_mode": "translation",
    "acfe_form": 0,
    "acfe_meta": {
        "acfcloneindex": {
            "acfe_meta_key": "",
            "acfe_meta_value": ""
        }
    },
    "acfe_note": "",
    "modified": 1767950738
}
